classroom_suite_mcp/__init__.py
classroom_suite_mcp/auth.py
classroom_suite_mcp/classroom.py
classroom_suite_mcp/docs.py
classroom_suite_mcp/drive.py
classroom_suite_mcp/server.py
classroom_suite_mcp-1.0.0.dist-info/METADATA
classroom_suite_mcp-1.0.0.dist-info/WHEEL
classroom_suite_mcp-1.0.0.dist-info/entry_points.txt
classroom_suite_mcp-1.0.0.dist-info/licenses/LICENSE
classroom_suite_mcp-1.0.0.dist-info/RECORD
