Metadata-Version: 2.4
Name: classroom-suite-mcp
Version: 1.0.0
Summary: Unified MCP server for Google Classroom, Drive, and Docs - seamlessly integrate education tools with AI assistants
Project-URL: Homepage, https://github.com/YOUR_USERNAME/classroom-suite-mcp
Project-URL: Repository, https://github.com/YOUR_USERNAME/classroom-suite-mcp
Project-URL: Documentation, https://github.com/YOUR_USERNAME/classroom-suite-mcp#readme
Project-URL: Issues, https://github.com/YOUR_USERNAME/classroom-suite-mcp/issues
Author-email: Your Name <your@email.com>
License: MIT
License-File: LICENSE
Keywords: ai,automation,education,google-classroom,google-docs,google-drive,mcp,model-context-protocol
Classifier: Development Status :: 4 - Beta
Classifier: Intended Audience :: Developers
Classifier: Intended Audience :: Education
Classifier: License :: OSI Approved :: MIT License
Classifier: Programming Language :: Python :: 3
Classifier: Programming Language :: Python :: 3.10
Classifier: Programming Language :: Python :: 3.11
Classifier: Programming Language :: Python :: 3.12
Classifier: Topic :: Education
Classifier: Topic :: Software Development :: Libraries :: Python Modules
Requires-Python: >=3.10
Requires-Dist: fastmcp>=2.0.0
Requires-Dist: google-api-python-client>=2.0.0
Requires-Dist: google-auth-oauthlib>=1.0.0
Requires-Dist: google-auth>=2.0.0
Requires-Dist: python-dotenv>=1.0.0
